query_segmenter/__init__.py
query_segmenter/unsupervised.py
query_segmenter-0.0.1.dist-info/LICENSE
query_segmenter-0.0.1.dist-info/METADATA
query_segmenter-0.0.1.dist-info/WHEEL
query_segmenter-0.0.1.dist-info/top_level.txt
query_segmenter-0.0.1.dist-info/RECORD
